jjckBackendDeployment/DockerActive.py
jjckBackendDeployment/K8sActive.py
jjckBackendDeployment/ProjcetActive.py
jjckBackendDeployment/__init__.py
jjckBackendDeployment/__main__.py
jjckBackendDeployment/kubeconfig.yaml
jjckBackendDeployment/nginx-deployment.yaml
jjckBackendDeployment-1.dist-info/METADATA
jjckBackendDeployment-1.dist-info/WHEEL
jjckBackendDeployment-1.dist-info/top_level.txt
jjckBackendDeployment-1.dist-info/RECORD
